Execute/memoryBank.v
`timescale 1ns/1ps
module memoryBank (mem_data_out,mem_data_in,mem_addr_out,mem_addr_in,r_w,reset,clk);
output reg [7:0] mem_data_out; // data to be fetched from mem
input [7:0] mem_data_in; // data to be saved in mem
input [3:0] mem_addr_in,mem_addr_out;// addr_in for address where data to be saved 
// addr_out for address from where data is collected for output.
input r_w,reset,clk;
integer i;

reg [7:0] memory [0:15]; // 16 memory locations  , 8 bit each

initial begin
    $readmemb("datamem.txt",memory); // feeding data to the memory;
end
always @(*) 
begin
    if(reset)
    begin
        for(i = 0 ; i < 15 ; i = i+1)
    begin
        memory[i] <= 8'b0;
    end
    end
    else
    begin
        if(r_w)
        begin
            mem_data_out <= memory[mem_addr_out];
        end
        else
        begin
            memory[mem_addr_in] <= mem_data_in;
        end
    end
end

endmodule //memoryBank

regFile.v
`timescale 1ns/1ps
module regFile (
output reg [7:0] rs1_data,rs2_data, // data to be fetched from rs1 and rs2,
input [2:0] rs1_addr,rs2_addr,rd_addr,
input [15:0] rd_data, // data to be saved in rd,
input reset,
input input_length, // 0 will mean rd_data is of 8 bits and 1 will mean it is of 16 bits,
input r_w // 1 for read and 0 for write,
);
integer i = 0;
reg [7:0] registers [0:7];

initial begin
    $readmemb("regdata.txt",registers); // feeding data to the regbank
end

always @(*) begin
    if(reset)
    begin
        $readmemb("regdata.txt",registers);
    end
    else
    begin
        if(r_w == 1)
        begin
            rs1_data <= registers[rs1_addr];
            rs2_data <= registers[rs2_addr];
        end
        else if(r_w == 0)
        begin
            if(input_length == 1'b0)
            begin
                registers[rd_addr] <= rd_data[7:0];
            end
            else if(input_length == 1'b1)
            begin
                registers[rd_addr] <= rd_data[15:8];
                registers[rd_addr+1] <= rd_data[7:0];
            end
        end
        else
        begin
        end
    end
end


endmodule //regFile

Execute/executestage.v
`timescale 1ns/1ps
`include "memoryBank.v"
`include "regFile.v"
module executestage (result,zero_flag,carry_flag,ac_flag,parity_flag,opcode,
am,rd,rs1,rs2,mem_addr,instr_mem_addr,s_r_amount,enable,reset,clk);
output  reg [15:0] result; // final output from stage;
output reg zero_flag,carry_flag,ac_flag,parity_flag; // all flag registers;

input [4:0] opcode;
input [2:0] s_r_amount;
input am; // addressing mode;
input enable,reset,clk;
input [2:0] rd,rs1,rs2; // register addereses recieved from prev stages;
input [3:0] mem_addr;
input [5:0] instr_mem_addr; // memory addr. recieved from prev stages;

wire [7:0] rs2_data,operand_1,mem_data;
wire [15:0] rd_data;

reg [7:0] operand_2;
reg[2:0] mux_1_out; // to decide from where the operand_1 will come;
reg [7:0] temp;

integer i;

regFile r1(operand_1,rs2_data,mux_1_out,rs2,rd,rd_data,1'b1,1'b0,1'bx);
memoryBank m1(mem_data,8'b0,mem_addr,4'b0,1'b1,1'b0,clk);

always @( *) begin

    if(opcode == 5'b00101 || opcode == 5'b00110 || opcode == 5'b01001 || opcode == 5'b10000
    || opcode == 5'b10001 || opcode == 5'b10010 || opcode == 5'b10011 || opcode == 5'b10100
    || opcode == 5'b10101 || opcode == 5'b01100)
    begin
        mux_1_out <= rd;
    end
    else 
    begin
        mux_1_out <= rs1;
    end

    if(am == 0)
    begin 
        operand_2 <= rs2_data; // operand 2 will be reg data;
    end
    else if(am == 1)
    begin
        operand_2 <= mem_data; // operand 2 will be mem data;
    end
end

    always @(*) 
begin
    if(reset)
    begin
        result <= 16'b0;
    end
    else
        begin
        if(enable)
            begin
            case(opcode)
                5'b00000 : begin
                result[15:8] <= 8'bx;
                if(am == 0)
                result[7:0] <= operand_1;
                else
                result[7:0] <= operand_2;
                end // move

                5'b00001 : begin
                    result[15:8] <= 8'bx;
                    {carry_flag,result[7:0]} <= operand_1 + operand_2;
                    end // addition {done [8:0] so that we can detect carry from the 9th bit}

                5'b00010 : begin
                    result[15:8] <= 8'bx;
                    {carry_flag,result[7:0]} <= operand_1 - operand_2;
                    end // subtraction

                5'b00011 : result <= operand_1 * operand_2; // multiplication
                
                5'b00100 : begin 
                    result[7:0] <= operand_1 / operand_2;
                    result[15:8] <= operand_1 % operand_2;
                end // division

                5'b00101 : begin
                    result[15:8] <= 8'bx;
                    if(am == 0)
                    {carry_flag,result[7:0]} <= operand_1 + 1;
                    else
                    {carry_flag,result[7:0]} <= operand_2 + 1;
                    end // increment

                5'b00110 : begin
                    result[15:8] <= 8'bx;
                    if(am == 0)
                    {carry_flag,result[7:0]} <= operand_1 - 1;
                    else
                    {carry_flag,result[7:0]} <= operand_2 - 1;
                    end // decrement

                5'b00111 : begin
                    result[15:8] <= 8'bx;
                    result[7:0] <= operand_1 & operand_2;
                    end // AND

                5'b01000 : begin
                    result[15:8] <= 8'bx;
                    result[7:0] <= operand_1 | operand_2;
                    end // OR

                5'b01001 : begin
                    result[15:8] <= 8'bx;
                    if(am == 0)
                    result[7:0] <= ~operand_1;
                    else
                    result[7:0] <= ~operand_2;
                    end // NOT

                5'b01010 : begin
                    result[15:8] <= 8'bx;
                    result[7:0] <= operand_1 ^ operand_2;
                    end // XOR

                5'b01011 : begin
                    result[15:8] <= 8'bx;
                    result[7:0] <= mem_data;
                    end // load mem to reg;

                5'b01100 : begin
                    result[15:8] <= 8'bx;
                    result[7:0] <= operand_1;
                    end // load reg to mem;    

                5'b01101 : begin
                    result[15:0] <= 16'bx;
                    end // jump

                5'b01110 || 5'b10110 || 5'b10111 || 5'b11000 : begin
                    result[7:0] <= 8'bx;
                    end // branch

                5'b10000 : begin
                    result[15:8] <= 8'bx;
                    if(am == 0)
                    {carry_flag,result[7:0]} <= operand_1[7:0] << s_r_amount;
                    else
                    {carry_flag,result[7:0]} <= operand_2[7:0] << s_r_amount;
                    end // arithmetic shift left

                5'b10001 : begin
                    result[15:8] <= 8'bx;
                    if(am==0)
                    temp = operand_1;
                    else
                    temp = operand_2;
                    for (i = 0; i < s_r_amount; i = i + 1) begin
                        carry_flag = temp[0];
                        temp[7:0] = {temp[7],temp[7:1]}; 
                    end
                    result[7:0] = temp;
                    end // arithmetic shift right 

                5'b10010 : begin
                    result[15:8] <= 8'bx;
                    if(am == 0)
                    {carry_flag,result[7:0]} <= operand_1[7:0] << s_r_amount; 
                    else
                    {carry_flag,result[7:0]} <= operand_2[7:0] << s_r_amount; 
                    end // logical shift left

                5'b10011 : begin
                    result[15:8] <= 8'bx;
                    if(am == 0)
                    {result[7:0],carry_flag} <= operand_1[7:0] >> s_r_amount;  
                    else                    
                    {result[7:0],carry_flag} <= operand_2[7:0] >> s_r_amount;  
                    end // logical shift right

                5'b10100 : begin
                    result[15:8] <= 8'bx;
                    if(am == 0)
                    temp = operand_1;
                    else
                    temp = operand_2;
                    for (i = 0; i < s_r_amount; i = i + 1) begin
                    temp[7:0] = {temp[6:0],temp[7]};
                    end
                    result[7:0] = temp;
                end // rotate left

                5'b10101 : begin
                    result[15:8] <= 8'bx;
                    if(am == 0)
                    temp = operand_1;
                    else
                    temp = operand_2;
                    for (i = 0; i < s_r_amount; i = i + 1) begin
                    temp[7:0] = {temp[0],temp[7:1]};
                    end
                    result[7:0] = temp;
                end // rotate right;

                5'b11001 : begin
                    result[15:1] <= 15'bx;
                    if(operand_1 >= operand_2)
                    result[0] <= 1;
                    else
                    result[0] <= 0;
                end // compare;

                5'b11111 : result <= 8'bx;
                default : begin
                     result <= 8'bx;
                    end // halt
                    
            endcase
            end
        else
        begin
            result <= 8'bx;
        end
    end

    // updating zero_flag
    if(opcode == 5'b00011)
    begin
        if(result == 0)
            begin
            zero_flag <= 1;
            end
        else 
            zero_flag <= 0;
    end
    else
    begin
        if(result[7:0] == 0)
            begin
            zero_flag <= 1;
            end
        else 
            zero_flag <= 0;
    end

    // updating carry_flag during the operation

    // updating auxilliary carry - ac_flag
    if(opcode == 5'b00001) // addition case
    begin
        {ac_flag,temp[3:0]} = operand_1[3:0] + operand_2[3:0];
    end
    else if(opcode == 5'b00010) // subtraction case
    begin
        {ac_flag,temp[3:0]} = {1'b0,operand_1[3:0]} - {1'b0,operand_2[3:0]};
    end
    else if(opcode == 5'b00101) // increment case
    begin
        {ac_flag,temp[3:0]} = operand_1[3:0] + 1'b1;
    end
    else if(opcode == 5'b00110) // decrement case
    begin
        {ac_flag,temp[3:0]} = {1'b0,operand_1[3:0]} - 1'b1;
    end

    // updating parity_flag
    if(opcode == 5'b00011)
    begin
        parity_flag = 0;
        for(i = 0 ; i < 16 ; i = i + 1)
        begin
        parity_flag = parity_flag^result[i];
        end
    end
    else if(opcode == 5'b11001)
    begin
        parity_flag = 0;
        parity_flag = parity_flag^result[0];
    end
    else if(opcode ==5'b01110 || opcode == 5'b10110 || opcode == 5'b10111 
    || opcode == 5'b11000 || opcode == 5'b01011 || opcode == 5'b01100)
    begin
    parity_flag = parity_flag;
    end
    else
    begin
        parity_flag = 0;
        for(i = 0 ; i < 8 ; i = i + 1)
        begin
            parity_flag = parity_flag^result[i];
        end
    end

end
endmodule //execute
/* ./iverilog -o execute.vvp executetb.v
 ./vvp execute.vvp */

executetb.v
`timescale 1ns/1ps
`include "executestage.v"
module executetb ();

wire [15:0] result; 
reg [4:0] opcode;
reg am;
reg enable,reset;
reg [2:0] rd,rs1,rs2,s_r_amount;
reg [3:0] mem_addr;
reg [5:0] instr_mem_addr;
reg clk;
wire zero_flag,carry_flag,ac_flag,parity_flag;

executestage dut(.zero_flag(zero_flag),.result(result),.opcode(opcode),.am(am),.enable(enable),.reset(reset)
,.rd(rd),.rs1(rs1),.rs2(rs2),.mem_addr(mem_addr),.instr_mem_addr(instr_mem_addr),.clk(clk),.s_r_amount(s_r_amount)
,.carry_flag(carry_flag),.ac_flag(ac_flag),.parity_flag(parity_flag));

initial
begin
    clk = 1'b0;
    forever 
    begin
        #5 clk = ~clk;
    end
end
initial
begin
   $dumpfile("execute.vcd");
   $dumpvars(0,executetb);
   $monitor("opcode: %b , am: %b , rd: %b, rs1: %b, rs2: %b, result: %b, zero_flag: %b, carry_flag: %b, parity_flag: %b, ac_flag: %b",
   opcode,am,rd,rs1,rs2,result,zero_flag,carry_flag,parity_flag,ac_flag);
    #2;
    opcode <= 5'b00011; am <= 1'b0; rd <= 3'b100; rs1 <= 3'b101; s_r_amount <= 1'bz; 
    rs2 <= 3'b111; mem_addr<= 4'bzzzz; enable <= 1'b1; reset <=1'b0;
    #5;
    opcode <= 5'b00001; am <= 1'b0; rd <= 3'b100; rs1 <= 3'b101; s_r_amount <= 1'bz;
    rs2 <= 3'b111; mem_addr<= 4'bzzzz; enable <= 1'b1; reset <=1'b0;
    #5;
    opcode <= 5'b01010; am <= 1'b0; rd <= 3'b100; rs1 <= 3'b101; s_r_amount <= 1'bz;
    rs2 <= 3'b111; mem_addr<= 4'bzzzz; enable <= 1'b1; reset <=1'b0;
    #5;
    opcode <= 5'b01110; am <= 1'b0; rd <= 3'bzzz; rs1 <= 3'bzzz; s_r_amount <= 3'bzzz;
    rs2 <= 3'bzzz; mem_addr<= 4'bzzzz; enable <= 1'b1; reset <=1'b0;
    #5;
    opcode <= 5'b01011; am <= 1'b0; rd <= 3'b100; rs1 <= 3'bzzz; s_r_amount <= 3'bzzz;
    rs2 <= 3'bzzz; mem_addr<= 4'bzzzz; enable <= 1'b1; reset <=1'b0;
    #5;
    opcode <= 5'b10100; am <= 1'b0; rd <= 3'b111; rs1 <= 3'bzzz; s_r_amount <= 3'b001;
    rs2 <= 3'bzzz; mem_addr<= 4'bzzzz; enable <= 1'b1; reset <=1'b0;
    #5;
    opcode <= 5'b10010; am <= 1'b0; rd <= 3'b111; rs1 <= 3'bzzz; s_r_amount <= 3'b001;
    rs2 <= 3'bzzz; mem_addr<= 4'bzzzz; enable <= 1'b1; reset <=1'b0;
    #5;
    opcode <= 5'b10000; am <= 1'b0; rd <= 3'b111; rs1 <= 3'bzzz; s_r_amount <= 3'b001;
    rs2 <= 3'bzzz; mem_addr<= 4'bzzzz; enable <= 1'b1; reset <=1'b0;
    #5;
    opcode <= 5'b00101; am <= 1'b0; rd <= 3'b111; rs1 <= 3'bzzz; s_r_amount <= 3'bzzz;
    rs2 <= 3'bzzz; mem_addr<= 4'bzzzz; enable <= 1'b1; reset <=1'b0;
    #5;
    opcode <= 5'b11111; am <= 1'bz; rd <= 3'bzzz; rs1 <= 3'bzzz; s_r_amount <= 3'bzzz;
    rs2 <= 3'bzzz; mem_addr<= 4'bzzzz; enable <= 1'b1; reset <=1'b0;
    #50 $finish;
end
endmodule //executetb
/* ./iverilog -o execute.vvp executetb.v
./vvp execute.vvp */

Execute/execute.vcd
$date
	Thu Jul 25 03:29:41 2024
$end
$version
	Icarus Verilog
$end
$timescale
	1ps
$end
$scope module executetb $end
$var wire 1 ! zero_flag $end
$var wire 16 " result [15:0] $end
$var wire 1 # parity_flag $end
$var wire 1 $ carry_flag $end
$var wire 1 % ac_flag $end
$var reg 1 & am $end
$var reg 1 ' clk $end
$var reg 1 ( enable $end
$var reg 6 ) instr_mem_addr [5:0] $end
$var reg 4 * mem_addr [3:0] $end
$var reg 5 + opcode [4:0] $end
$var reg 3 , rd [2:0] $end
$var reg 1 - reset $end
$var reg 3 . rs1 [2:0] $end
$var reg 3 / rs2 [2:0] $end
$var reg 3 0 s_r_amount [2:0] $end
$scope module dut $end
$var wire 1 & am $end
$var wire 1 ' clk $end
$var wire 1 ( enable $end
$var wire 6 1 instr_mem_addr [5:0] $end
$var wire 4 2 mem_addr [3:0] $end
$var wire 5 3 opcode [4:0] $end
$var wire 3 4 rd [2:0] $end
$var wire 16 5 rd_data [15:0] $end
$var wire 1 - reset $end
$var wire 3 6 rs1 [2:0] $end
$var wire 3 7 rs2 [2:0] $end
$var wire 3 8 s_r_amount [2:0] $end
$var wire 8 9 rs2_data [7:0] $end
$var wire 8 : operand_1 [7:0] $end
$var wire 8 ; mem_data [7:0] $end
$var reg 1 % ac_flag $end
$var reg 1 $ carry_flag $end
$var reg 3 < mux_1_out [2:0] $end
$var reg 8 = operand_2 [7:0] $end
$var reg 1 # parity_flag $end
$var reg 16 > result [15:0] $end
$var reg 8 ? temp [7:0] $end
$var reg 1 ! zero_flag $end
$var integer 32 @ i [31:0] $end
$scope module m1 $end
$var wire 1 ' clk $end
$var wire 4 A mem_addr_in [3:0] $end
$var wire 4 B mem_addr_out [3:0] $end
$var wire 8 C mem_data_in [7:0] $end
$var wire 1 D r_w $end
$var wire 1 E reset $end
$var reg 8 F mem_data_out [7:0] $end
$var integer 32 G i [31:0] $end
$upscope $end
$scope module r1 $end
$var wire 1 H input_length $end
$var wire 1 I r_w $end
$var wire 3 J rd_addr [2:0] $end
$var wire 16 K rd_data [15:0] $end
$var wire 1 L reset $end
$var wire 3 M rs1_addr [2:0] $end
$var wire 3 N rs2_addr [2:0] $end
$var reg 8 O rs1_data [7:0] $end
$var reg 8 P rs2_data [7:0] $end
$var integer 32 Q i [31:0] $end
$upscope $end
$upscope $end
$upscope $end
$enddefinitions $end
$comment Show the parameter values. $end
$dumpall
$end
#0
$dumpvars
b0 Q
bx P
bx O
bx N
bx M
0L
bz K
bx J
1I
xH
bx G
bx F
0E
1D
b0 C
bx B
b0 A
bx @
bx ?
bx >
bx =
bx <
bx ;
bx :
bx 9
bx 8
bx 7
bx 6
bz 5
bx 4
bx 3
bx 2
bx 1
bx 0
bx /
bx .
x-
bx ,
bx +
bx *
bx )
x(
0'
x&
x%
x$
x#
bx "
x!
$end
#2000
b100011 "
b100011 >
b111 =
b101 :
b101 O
b111 9
b111 P
0!
b101 <
b101 M
b10000 @
1#
0-
1(
bz *
bz 2
bz B
b111 /
b111 7
b111 N
b0z 0
b0z 8
b101 .
b101 6
b100 ,
b100 4
b100 J
0&
b11 +
b11 3
#5000
1'
#7000
0$
bx00001100 "
bx00001100 >
b1000 @
0#
0%
bx1100 ?
b1 +
b1 3
#10000
0'
#12000
bx00000010 "
bx00000010 >
1#
b1000 @
b1010 +
b1010 3
#15000
1'
#17000
bx =
bx :
bx O
bx 9
bx P
b0xxxxxxxx "
b0xxxxxxxx >
bz <
bz M
bz /
bz 7
bz N
bz 0
bz 8
bz .
bz 6
bz ,
bz 4
bz J
b1110 +
b1110 3
#20000
0'
#22000
bx "
bx >
b100 ,
b100 4
b100 J
b1011 +
b1011 3
#25000
1'
#27000
bx00001110 "
bx00001110 >
b111 :
b111 O
b111 <
b111 M
1#
b1000 @
b1110 ?
b1 0
b1 8
b111 ,
b111 4
b111 J
b10100 +
b10100 3
#30000
0'
#32000
b1000 @
1#
b10010 +
b10010 3
#35000
1'
#37000
b1000 @
1#
b10000 +
b10000 3
#40000
0'
#42000
bx00001000 "
bx00001000 >
b1000 @
1#
b1000 ?
bz 0
bz 8
b101 +
b101 3
#45000
1'
#47000
bx :
bx O
b0xxxxxxxx "
b0xxxxxxxx >
bz <
bz M
b1000 @
x#
bz ,
bz 4
bz J
z&
b11111 +
b11111 3
